dvr_ftp_tools-0.1.0.dist-info/licenses/LICENSE
ftp_tools/__init__.py
ftp_tools/client.py
dvr_ftp_tools-0.1.0.dist-info/METADATA
dvr_ftp_tools-0.1.0.dist-info/WHEEL
dvr_ftp_tools-0.1.0.dist-info/top_level.txt
dvr_ftp_tools-0.1.0.dist-info/RECORD
