Metadata-Version: 2.4
Name: dvr_ftp_tools
Version: 0.1.0
Summary: Ferramentas para listar e baixar arquivos de DVR via FTP
Author: Edilson claudino da silva
Author-email: Seu Nome <seu@email.com>
Project-URL: Homepage, https://github.com/seuusuario/meu_projeto_ftp
Classifier: Programming Language :: Python :: 3
Classifier: License :: OSI Approved :: MIT License
Classifier: Operating System :: OS Independent
Requires-Python: >=3.6
License-File: LICENSE
Dynamic: author
Dynamic: license-file
Dynamic: requires-python
